bthomehub5_devicelist/__init__.py
bthomehub5_devicelist/bthomehub5_devicelist.py
bthomehub5_devicelist-0.1.1.dist-info/METADATA
bthomehub5_devicelist-0.1.1.dist-info/RECORD
bthomehub5_devicelist-0.1.1.dist-info/WHEEL
bthomehub5_devicelist-0.1.1.dist-info/top_level.txt
