Metadata-Version: 2.1
Name: bthomehub5-devicelist
Version: 0.1.1
Summary: A library that returns a list of devices currently connected to a BT Home Hub 5
Home-page: https://github.com/ahobsonsayers/bthomehub5-devicelist
Author: Arran Hobson Sayers
Author-email: ahobsonsayers@gmail.com
License: UNKNOWN
Platform: UNKNOWN
Classifier: Programming Language :: Python :: 3
Classifier: License :: OSI Approved :: MIT License
Classifier: Operating System :: OS Independent
